MANIFEST.in
README.rst
setup.py
include/fast_atof.h
include/fast_atoi.h
include/python3.6m/Python-ast.h
include/python3.6m/Python.h
include/python3.6m/abstract.h
include/python3.6m/accu.h
include/python3.6m/asdl.h
include/python3.6m/ast.h
include/python3.6m/bitset.h
include/python3.6m/bltinmodule.h
include/python3.6m/boolobject.h
include/python3.6m/bytearrayobject.h
include/python3.6m/bytes_methods.h
include/python3.6m/bytesobject.h
include/python3.6m/cellobject.h
include/python3.6m/ceval.h
include/python3.6m/classobject.h
include/python3.6m/code.h
include/python3.6m/codecs.h
include/python3.6m/compile.h
include/python3.6m/complexobject.h
include/python3.6m/datetime.h
include/python3.6m/descrobject.h
include/python3.6m/dictobject.h
include/python3.6m/dtoa.h
include/python3.6m/dynamic_annotations.h
include/python3.6m/enumobject.h
include/python3.6m/errcode.h
include/python3.6m/eval.h
include/python3.6m/fileobject.h
include/python3.6m/fileutils.h
include/python3.6m/floatobject.h
include/python3.6m/frameobject.h
include/python3.6m/funcobject.h
include/python3.6m/genobject.h
include/python3.6m/graminit.h
include/python3.6m/grammar.h
include/python3.6m/import.h
include/python3.6m/intrcheck.h
include/python3.6m/iterobject.h
include/python3.6m/listobject.h
include/python3.6m/longintrepr.h
include/python3.6m/longobject.h
include/python3.6m/marshal.h
include/python3.6m/memoryobject.h
include/python3.6m/metagrammar.h
include/python3.6m/methodobject.h
include/python3.6m/modsupport.h
include/python3.6m/moduleobject.h
include/python3.6m/namespaceobject.h
include/python3.6m/node.h
include/python3.6m/object.h
include/python3.6m/objimpl.h
include/python3.6m/odictobject.h
include/python3.6m/opcode.h
include/python3.6m/osdefs.h
include/python3.6m/osmodule.h
include/python3.6m/parsetok.h
include/python3.6m/patchlevel.h
include/python3.6m/pgen.h
include/python3.6m/pgenheaders.h
include/python3.6m/py_curses.h
include/python3.6m/pyarena.h
include/python3.6m/pyatomic.h
quantum_esperanto.egg-info/PKG-INFO
quantum_esperanto.egg-info/SOURCES.txt
quantum_esperanto.egg-info/dependency_links.txt
quantum_esperanto.egg-info/requires.txt
quantum_esperanto.egg-info/top_level.txt
