Metadata-Version: 2.1
Name: quantum-esperanto
Version: 0.3
Summary: A fast parser of XML files output by VASP DFT code written in Cython.
Home-page: https://github.com/tilde-lab/quantum_esperanto
Author: Andrey Sobolev
Author-email: andrey.n.sobolev@gmail.com
License: MIT
Platform: UNKNOWN
Classifier: Development Status :: 3 - Alpha
Classifier: Intended Audience :: Science/Research
Classifier: Topic :: Scientific/Engineering :: Chemistry
Classifier: Topic :: Scientific/Engineering :: Physics
Classifier: License :: OSI Approved :: MIT License
Classifier: Programming Language :: Python :: 2
Classifier: Programming Language :: Python :: 2.7
Classifier: Programming Language :: Python :: 3
Classifier: Programming Language :: Python :: 3.3
Classifier: Programming Language :: Python :: 3.4
Classifier: Programming Language :: Python :: 3.5
Classifier: Programming Language :: Python :: 3.6
Provides-Extra: dev
